 {
  "data2022": [
      {
        "CNT": 11,
        "lk-url": "006bb0a.netsolhost.com",
        "li-metrocity": "Austin",
        "lk-sic": "",
        "lk-employees": "",
        "lk-salesmillion": "",
        "lk-shortco": "Central Counties Mhmr",
        "CountMale": 2,
        "CountFemale": 9,
        "CountFemaleLevel_50": 1,
        "CountFemaleLevel_46": 1,
        "CountMaleLevel_50": "",
        "CountMaleLevel_46": ""
      },
      {
        "CNT": 5,
        "lk-url": "007law.com",
        "li-metrocity": "Portland",
        "lk-sic": 8111,
        "lk-employees": 2,
        "lk-salesmillion": 0.12,
        "lk-shortco": "Oliveros Law Group PC",
        "CountMale": 2,
        "CountFemale": 3,
        "CountFemaleLevel_50": "",
        "CountFemaleLevel_46": "",
        "CountMaleLevel_50": 1,
        "CountMaleLevel_46": 1
      },
      {
        "CNT": 6,
        "lk-url": "1000watt.net",
        "li-metrocity": "Portland",
        "lk-sic": 8742,
        "lk-employees": 6,
        "lk-salesmillion": 0.28,
        "lk-shortco": "1000Watt",
        "CountMale": 2,
        "CountFemale": 4,
        "CountFemaleLevel_50": 2,
        "CountFemaleLevel_46": 2,
        "CountMaleLevel_50": 1,
        "CountMaleLevel_46": 1
      },
      {
        "CNT": 11,
        "lk-url": "100blackmen-atlanta.org",
        "li-metrocity": "Atlanta",
        "lk-sic": 8641,
        "lk-employees": 20,
        "lk-salesmillion": 5.36,
        "lk-shortco": "100 Black Men of Atlanta",
        "CountMale": 5,
        "CountFemale": 5,
        "CountFemaleLevel_50": 2,
        "CountFemaleLevel_46": 2,
        "CountMaleLevel_50": 2,
        "CountMaleLevel_46": 2
      },
      {
        "CNT": 8,
        "lk-url": "100devs.org",
        "li-metrocity": "Los Angeles",
        "lk-sic": "",
        "lk-employees": "",
        "lk-salesmillion": "",
        "lk-shortco": "100Devs",
        "CountMale": 6,
        "CountFemale": 2,
        "CountFemaleLevel_50": "",
        "CountFemaleLevel_46": "",
        "CountMaleLevel_50": "",
        "CountMaleLevel_46": ""
      },
      {
        "CNT": 6,
        "lk-url": "100khomes.org",
        "li-metrocity": "Los Angeles",
        "lk-sic": 5251,
        "lk-employees": 9,
        "lk-salesmillion": 1.38,
        "lk-shortco": 100000,
        "CountMale": 4,
        "CountFemale": 2,
        "CountFemaleLevel_50": 2,
        "CountFemaleLevel_46": 2,
        "CountMaleLevel_50": 3,
        "CountMaleLevel_46": 3
      },
      {
        "CNT": 5,
        "lk-url": "100percentchiropractic.com",
        "li-metrocity": "San Diego",
        "lk-sic": 8041,
        "lk-employees": 2,
        "lk-salesmillion": 0.04,
        "lk-shortco": "100% Chiropractic",
        "CountMale": 5,
        "CountFemale": "",
        "CountFemaleLevel_50": "",
        "CountFemaleLevel_46": "",
        "CountMaleLevel_50": 3,
        "CountMaleLevel_46": 3
      },
      {
        "CNT": 5,
        "lk-url": "1010data.com",
        "li-metrocity": "San Diego",
        "lk-sic": 7371,
        "lk-employees": "",
        "lk-salesmillion": "",
        "lk-shortco": "1010Data",
        "CountMale": 4,
        "CountFemale": 1,
        "CountFemaleLevel_50": "",
        "CountFemaleLevel_46": "",
        "CountMaleLevel_50": 1,
        "CountMaleLevel_46": 1
      },
      {
        "CNT": 6,
        "lk-url": "1013integrated.com",
        "li-metrocity": "Honolulu",
        "lk-sic": 7812,
        "lk-employees": 10,
        "lk-salesmillion": 0.76,
        "lk-shortco": "1013 Integrated",
        "CountMale": 3,
        "CountFemale": 3,
        "CountFemaleLevel_50": 2,
        "CountFemaleLevel_46": 2,
        "CountMaleLevel_50": 2,
        "CountMaleLevel_46": 2
      },
      {
        "CNT": 10,
        "lk-url": "1015.com",
        "li-metrocity": "San Francisco",
        "lk-sic": 5813,
        "lk-employees": 80,
        "lk-salesmillion": 2.5,
        "lk-shortco": "Ten15",
        "CountMale": 6,
        "CountFemale": 3,
        "CountFemaleLevel_50": 3,
        "CountFemaleLevel_46": 3,
        "CountMaleLevel_50": 1,
        "CountMaleLevel_46": 1
      },
      {
        "CNT": 8,
        "lk-url": "1021creative.com",
        "li-metrocity": "Los Angeles",
        "lk-sic": 9999,
        "lk-employees": 5,
        "lk-salesmillion": 0.09,
        "lk-shortco": "1021 Creative",
        "CountMale": 5,
        "CountFemale": 3,
        "CountFemaleLevel_50": 2,
        "CountFemaleLevel_46": 2,
        "CountMaleLevel_50": 2,
        "CountMaleLevel_46": 2
      },
      {
        "CNT": 7,
        "lk-url": "1031crowdfunding.com",
        "li-metrocity": "Orange County",
        "lk-sic": 6799,
        "lk-employees": 7,
        "lk-salesmillion": 0.21,
        "lk-shortco": "1031 CrowdFunding",
        "CountMale": 7,
        "CountFemale": "",
        "CountFemaleLevel_50": "",
        "CountFemaleLevel_46": "",
        "CountMaleLevel_50": 4,
        "CountMaleLevel_46": 4
      },
      {
        "CNT": 7,
        "lk-url": "1045realestate.com",
        "li-metrocity": "St Louis",
        "lk-sic": 6531,
        "lk-employees": 12,
        "lk-salesmillion": 0.21,
        "lk-shortco": 1045,
        "CountMale": 2,
        "CountFemale": 4,
        "CountFemaleLevel_50": 3,
        "CountFemaleLevel_46": 3,
        "CountMaleLevel_50": 2,
        "CountMaleLevel_46": 2
      },
      {
        "CNT": 19,
        "lk-url": "10fitness.com",
        "li-metrocity": "Little Rock",
        "lk-sic": 7991,
        "lk-employees": 25,
        "lk-salesmillion": 1.48,
        "lk-shortco": "10 Fitness",
        "CountMale": 11,
        "CountFemale": 8,
        "CountFemaleLevel_50": "",
        "CountFemaleLevel_46": "",
        "CountMaleLevel_50": 7,
        "CountMaleLevel_46": 7
      },
      {
        "CNT": 6,
        "lk-url": "10roadsexpress.com",
        "li-metrocity": "Omaha",
        "lk-sic": "",
        "lk-employees": "",
        "lk-salesmillion": "",
        "lk-shortco": "10 Roads Express",
        "CountMale": 5,
        "CountFemale": 1,
        "CountFemaleLevel_50": "",
        "CountFemaleLevel_46": "",
        "CountMaleLevel_50": 4,
        "CountMaleLevel_46": 4
      },
      {
        "CNT": 60,
        "lk-url": "10TampaBay.com",
        "li-metrocity": "Tampa",
        "lk-sic": 7622,
        "lk-employees": 1,
        "lk-salesmillion": 0.09,
        "lk-shortco": "Wtsptv",
        "CountMale": 28,
        "CountFemale": 32,
        "CountFemaleLevel_50": 12,
        "CountFemaleLevel_46": 12,
        "CountMaleLevel_50": 6,
        "CountMaleLevel_46": 6
      },
      {
        "CNT": 10,
        "lk-url": "10thst.com",
        "li-metrocity": "Los Angeles",
        "lk-sic": 7922,
        "lk-employees": 13,
        "lk-salesmillion": 0.39,
        "lk-shortco": "10th Street Entertainment",
        "CountMale": 6,
        "CountFemale": 4,
        "CountFemaleLevel_50": 3,
        "CountFemaleLevel_46": 3,
        "CountMaleLevel_50": 4,
        "CountMaleLevel_46": 4
      },
      {
        "CNT": 7,
        "lk-url": "10to1pr.com",
        "li-metrocity": "Phoenix",
        "lk-sic": 8743,
        "lk-employees": 1,
        "lk-salesmillion": 0.04,
        "lk-shortco": "10 to 1 Public Relations",
        "CountMale": 2,
        "CountFemale": 5,
        "CountFemaleLevel_50": 3,
        "CountFemaleLevel_46": 3,
        "CountMaleLevel_50": 2,
        "CountMaleLevel_46": 2
      },
      {
        "CNT": 61,
        "lk-url": "10xgenomics.com",
        "li-metrocity": "Silicon Valley",
        "lk-sic": 2836,
        "lk-employees": 149,
        "lk-salesmillion": 6.57,
        "lk-shortco": "10x Genomics",
        "CountMale": 33,
        "CountFemale": 27,
        "CountFemaleLevel_50": 11,
        "CountFemaleLevel_46": 11,
        "CountMaleLevel_50": 7,
        "CountMaleLevel_46": 7
      },
      {
        "CNT": 5,
        "lk-url": "10xpeople.com",
        "li-metrocity": "Denver",
        "lk-sic": "",
        "lk-employees": "",
        "lk-salesmillion": "",
        "lk-shortco": "10X People",
        "CountMale": 3,
        "CountFemale": 2,
        "CountFemaleLevel_50": 1,
        "CountFemaleLevel_46": 1,
        "CountMaleLevel_50": 1,
        "CountMaleLevel_46": 1
      },
      {
        "CNT": 5,
        "lk-url": "1111systems.com",
        "li-metrocity": "Austin",
        "lk-sic": 9999,
        "lk-employees": "",
        "lk-salesmillion": "",
        "lk-shortco": "iland Cloud",
        "CountMale": 5,
        "CountFemale": "",
        "CountFemaleLevel_50": "",
        "CountFemaleLevel_46": "",
        "CountMaleLevel_50": 3,
        "CountMaleLevel_46": 3
      },
      {
        "CNT": 5,
        "lk-url": "111attackwing.ang.af.mil",
        "li-metrocity": "Philadelphia",
        "lk-sic": 9711,
        "lk-employees": "",
        "lk-salesmillion": "",
        "lk-shortco": "111th Attack Wing Pennsylvania Air National Guard",
        "CountMale": 5,
        "CountFemale": "",
        "CountFemaleLevel_50": "",
        "CountFemaleLevel_46": "",
        "CountMaleLevel_50": "",
        "CountMaleLevel_46": ""
      },
      {
        "CNT": 22,
        "lk-url": "115fw.ang.af.mil",
        "li-metrocity": "Madison",
        "lk-sic": 4581,
        "lk-employees": 8,
        "lk-salesmillion": 0.71,
        "lk-shortco": "Air National Guard Wi 115th Fighter Wing",
        "CountMale": 17,
        "CountFemale": 5,
        "CountFemaleLevel_50": 3,
        "CountFemaleLevel_46": 3,
        "CountMaleLevel_50": 4,
        "CountMaleLevel_46": 4
      },
      {
        "CNT": 6,
        "lk-url": "115fw.ang.af.mil",
        "li-metrocity": "Milwaukee",
        "lk-sic": 4581,
        "lk-employees": 8,
        "lk-salesmillion": 0.71,
        "lk-shortco": "Air National Guard WI 115th Fighter Wing",
        "CountMale": 5,
        "CountFemale": 1,
        "CountFemaleLevel_50": "",
        "CountFemaleLevel_46": "",
        "CountMaleLevel_50": 1,
        "CountMaleLevel_46": 1
      },
      {
        "CNT": 163,
        "lk-url": "1199nbf.org",
        "li-metrocity": "New York",
        "lk-sic": 6722,
        "lk-employees": 7,
        "lk-salesmillion": 2.2,
        "lk-shortco": "1199 National Benefit Fund",
        "CountMale": 62,
        "CountFemale": 89,
        "CountFemaleLevel_50": 25,
        "CountFemaleLevel_46": 25,
        "CountMaleLevel_50": 11,
        "CountMaleLevel_46": 10
      },
      {
        "CNT": 5,
        "lk-url": "1199sandy.com",
        "li-metrocity": "New York",
        "lk-sic": "",
        "lk-employees": "",
        "lk-salesmillion": "",
        "lk-shortco": "1199 SEIU United Healthcare Workers East",
        "CountMale": 3,
        "CountFemale": 2,
        "CountFemaleLevel_50": 2,
        "CountFemaleLevel_46": 2,
        "CountMaleLevel_50": 2,
        "CountMaleLevel_46": 2
      },
      {
        "CNT": 31,
        "lk-url": "11alive.com",
        "li-metrocity": "Atlanta",
        "lk-sic": 4833,
        "lk-employees": 39,
        "lk-salesmillion": 4.97,
        "lk-shortco": "11Alive",
        "CountMale": 8,
        "CountFemale": 22,
        "CountFemaleLevel_50": 5,
        "CountFemaleLevel_46": 5,
        "CountMaleLevel_50": 1,
        "CountMaleLevel_46": 1
      },
      {
        "CNT": 10,
        "lk-url": "11honore.com",
        "li-metrocity": "Los Angeles",
        "lk-sic": "",
        "lk-employees": "",
        "lk-salesmillion": "",
        "lk-shortco": "11 Honoré",
        "CountMale": "",
        "CountFemale": 10,
        "CountFemaleLevel_50": 6,
        "CountFemaleLevel_46": 6,
        "CountMaleLevel_50": "",
        "CountMaleLevel_46": ""
      },
      {
        "CNT": 9,
        "lk-url": "11ten.com",
        "li-metrocity": "Atlanta",
        "lk-sic": "",
        "lk-employees": "",
        "lk-salesmillion": "",
        "lk-shortco": "11|TEN Innovation Partners",
        "CountMale": 7,
        "CountFemale": 2,
        "CountFemaleLevel_50": 1,
        "CountFemaleLevel_46": 1,
        "CountMaleLevel_50": 6,
        "CountMaleLevel_46": 6
      },
      {
        "CNT": 6,
        "lk-url": "11thhourtheatrecompany.org",
        "li-metrocity": "Philadelphia",
        "lk-sic": 7922,
        "lk-employees": 2,
        "lk-salesmillion": 0.3,
        "lk-shortco": "Eleventh Hour Studios",
        "CountMale": 3,
        "CountFemale": 2,
        "CountFemaleLevel_50": 2,
        "CountFemaleLevel_46": 2,
        "CountMaleLevel_50": 1,
        "CountMaleLevel_46": 1
      },
      {
        "CNT": 6,
        "lk-url": "11twentythree.com",
        "li-metrocity": "Omaha",
        "lk-sic": 7311,
        "lk-employees": 2,
        "lk-salesmillion": 0.27,
        "lk-shortco": "Eleven TwentyThree",
        "CountMale": 1,
        "CountFemale": 5,
        "CountFemaleLevel_50": 1,
        "CountFemaleLevel_46": 1,
        "CountMaleLevel_50": 1,
        "CountMaleLevel_46": 1
      },
      {
        "CNT": 36,
        "lk-url": "120water.com",
        "li-metrocity": "Indianapolis",
        "lk-sic": "",
        "lk-employees": "",
        "lk-salesmillion": "",
        "lk-shortco": "120Water",
        "CountMale": 23,
        "CountFemale": 12,
        "CountFemaleLevel_50": 6,
        "CountFemaleLevel_46": 6,
        "CountMaleLevel_50": 12,
        "CountMaleLevel_46": 12
      },
      {
        "CNT": 13,
        "lk-url": "121.health",
        "li-metrocity": "Nashville",
        "lk-sic": "",
        "lk-employees": "",
        "lk-salesmillion": "",
        "lk-shortco": "OnetoOne Health",
        "CountMale": 2,
        "CountFemale": 11,
        "CountFemaleLevel_50": 4,
        "CountFemaleLevel_46": 4,
        "CountMaleLevel_50": "",
        "CountMaleLevel_46": ""
      },
      {
        "CNT": 7,
        "lk-url": "1218global.com",
        "li-metrocity": "Dallas",
        "lk-sic": 8741,
        "lk-employees": 2,
        "lk-salesmillion": 0.11,
        "lk-shortco": "1218 Global",
        "CountMale": 2,
        "CountFemale": 5,
        "CountFemaleLevel_50": 2,
        "CountFemaleLevel_46": 2,
        "CountMaleLevel_50": 2,
        "CountMaleLevel_46": 2
      },
      {
        "CNT": 29,
        "lk-url": "121corp.com",
        "li-metrocity": "Washington",
        "lk-sic": 7336,
        "lk-employees": 3,
        "lk-salesmillion": 0.3,
        "lk-shortco": "USA",
        "CountMale": 11,
        "CountFemale": 15,
        "CountFemaleLevel_50": 3,
        "CountFemaleLevel_46": 3,
        "CountMaleLevel_50": 5,
        "CountMaleLevel_46": 5
      },
      {
        "CNT": 5,
        "lk-url": "121realty.com",
        "li-metrocity": "Denver",
        "lk-sic": 6531,
        "lk-employees": "",
        "lk-salesmillion": "",
        "lk-shortco": "121 Realty",
        "CountMale": 1,
        "CountFemale": 4,
        "CountFemaleLevel_50": 1,
        "CountFemaleLevel_46": 1,
        "CountMaleLevel_50": "",
        "CountMaleLevel_46": ""
      },
      {
        "CNT": 6,
        "lk-url": "123.net",
        "li-metrocity": "Grand Rapids",
        "lk-sic": 7374,
        "lk-employees": 2,
        "lk-salesmillion": 0.04,
        "lk-shortco": "123Net",
        "CountMale": 5,
        "CountFemale": 1,
        "CountFemaleLevel_50": 1,
        "CountFemaleLevel_46": 1,
        "CountMaleLevel_50": 2,
        "CountMaleLevel_46": 2
      },
      {
        "CNT": 8,
        "lk-url": "123homecares.com",
        "li-metrocity": "Austin",
        "lk-sic": 8082,
        "lk-employees": 8,
        "lk-salesmillion": 0.06,
        "lk-shortco": "123 Home Care",
        "CountMale": 3,
        "CountFemale": 5,
        "CountFemaleLevel_50": 3,
        "CountFemaleLevel_46": 3,
        "CountMaleLevel_50": 3,
        "CountMaleLevel_46": 3
      },
      {
        "CNT": 7,
        "lk-url": "123people.com",
        "li-metrocity": "Houston",
        "lk-sic": 9999,
        "lk-employees": 7,
        "lk-salesmillion": 0.09,
        "lk-shortco": 123,
        "CountMale": 4,
        "CountFemale": 2,
        "CountFemaleLevel_50": "",
        "CountFemaleLevel_46": "",
        "CountMaleLevel_50": 1,
        "CountMaleLevel_46": 1
      },
      {
        "CNT": 6,
        "lk-url": "12Mortgage.com",
        "li-metrocity": "San Diego",
        "lk-sic": 6799,
        "lk-employees": 2,
        "lk-salesmillion": 0.08,
        "lk-shortco": "Realty Capital",
        "CountMale": 4,
        "CountFemale": 2,
        "CountFemaleLevel_50": "",
        "CountFemaleLevel_46": "",
        "CountMaleLevel_50": 3,
        "CountMaleLevel_46": 3
      },
      {
        "CNT": 62,
        "lk-url": "12News.com",
        "li-metrocity": "Phoenix",
        "lk-sic": 4833,
        "lk-employees": 200,
        "lk-salesmillion": 15.55,
        "lk-shortco": "12 News KPNXTV NBC",
        "CountMale": 34,
        "CountFemale": 26,
        "CountFemaleLevel_50": 15,
        "CountFemaleLevel_46": 15,
        "CountMaleLevel_50": 13,
        "CountMaleLevel_46": 13
      },
      {
        "CNT": 7,
        "lk-url": "133.clayton.k12.ga.us",
        "li-metrocity": "Atlanta",
        "lk-sic": 8211,
        "lk-employees": "",
        "lk-salesmillion": "",
        "lk-shortco": "Callaway Elementary School",
        "CountMale": 1,
        "CountFemale": 6,
        "CountFemaleLevel_50": "",
        "CountFemaleLevel_46": "",
        "CountMaleLevel_50": "",
        "CountMaleLevel_46": ""
      },
      {
        "CNT": 25,
        "lk-url": "13coins.com",
        "li-metrocity": "Seattle",
        "lk-sic": 5812,
        "lk-employees": 160,
        "lk-salesmillion": 6.03,
        "lk-shortco": "13 Coins Restaurants",
        "CountMale": 18,
        "CountFemale": 6,
        "CountFemaleLevel_50": 4,
        "CountFemaleLevel_46": 4,
        "CountMaleLevel_50": 6,
        "CountMaleLevel_46": 6
      },
      {
        "CNT": 8,
        "lk-url": "13districtcourt.com",
        "li-metrocity": "Albuquerque",
        "lk-sic": 9211,
        "lk-employees": "",
        "lk-salesmillion": "",
        "lk-shortco": "13th Judicial District Court",
        "CountMale": 4,
        "CountFemale": 4,
        "CountFemaleLevel_50": "",
        "CountFemaleLevel_46": "",
        "CountMaleLevel_50": 2,
        "CountMaleLevel_46": 2
      },
      {
        "CNT": 7,
        "lk-url": "13emerueuniversal.fr",
        "li-metrocity": "Los Angeles",
        "lk-sic": "",
        "lk-employees": "",
        "lk-salesmillion": "",
        "lk-shortco": "Actively Seeking Employment",
        "CountMale": 4,
        "CountFemale": 3,
        "CountFemaleLevel_50": "",
        "CountFemaleLevel_46": "",
        "CountMaleLevel_50": "",
        "CountMaleLevel_46": ""
      },
      {
        "CNT": 13,
        "lk-url": "13fi.com",
        "li-metrocity": "Miami",
        "lk-sic": 6799,
        "lk-employees": 3,
        "lk-salesmillion": 0.65,
        "lk-shortco": "13th Floor Investments",
        "CountMale": 9,
        "CountFemale": 4,
        "CountFemaleLevel_50": 2,
        "CountFemaleLevel_46": 2,
        "CountMaleLevel_50": 7,
        "CountMaleLevel_46": 7
      },
      {
        "CNT": 52,
        "lk-url": "13newsnow.com",
        "li-metrocity": "Norfolk",
        "lk-sic": 4833,
        "lk-employees": 160,
        "lk-salesmillion": 20.4,
        "lk-shortco": "13News Now WVEC",
        "CountMale": 26,
        "CountFemale": 24,
        "CountFemaleLevel_50": 8,
        "CountFemaleLevel_46": 8,
        "CountMaleLevel_50": 10,
        "CountMaleLevel_46": 10
      },
      {
        "CNT": 5,
        "lk-url": "13thfloorhauntedhouses.com",
        "li-metrocity": "Chicago",
        "lk-sic": 9999,
        "lk-employees": 5,
        "lk-salesmillion": 0.14,
        "lk-shortco": "Svenpuss Productions",
        "CountMale": 3,
        "CountFemale": 2,
        "CountFemaleLevel_50": "",
        "CountFemaleLevel_46": "",
        "CountMaleLevel_50": "",
        "CountMaleLevel_46": ""
      },
      {
        "CNT": 6,
        "lk-url": "13thfloorhomes.com",
        "li-metrocity": "Miami",
        "lk-sic": 6512,
        "lk-employees": 2,
        "lk-salesmillion": 0.09,
        "lk-shortco": "13th Floor Homes",
        "CountMale": 2,
        "CountFemale": 4,
        "CountFemaleLevel_50": 3,
        "CountFemaleLevel_46": 3,
        "CountMaleLevel_50": 2,
        "CountMaleLevel_46": 2
      },
      {
        "CNT": 7,
        "lk-url": "1469autobody.com",
        "li-metrocity": "Indianapolis",
        "lk-sic": 7532,
        "lk-employees": 21,
        "lk-salesmillion": 2.04,
        "lk-shortco": "1469 Autobody",
        "CountMale": 4,
        "CountFemale": 1,
        "CountFemaleLevel_50": "",
        "CountFemaleLevel_46": "",
        "CountMaleLevel_50": 3,
        "CountMaleLevel_46": 3
      },
      {
        "CNT": 7,
        "lk-url": "14streetmedical.com",
        "li-metrocity": "New York",
        "lk-sic": 5571,
        "lk-employees": 5,
        "lk-salesmillion": 0.36,
        "lk-shortco": "14 Street Medical PC",
        "CountMale": 3,
        "CountFemale": 3,
        "CountFemaleLevel_50": "",
        "CountFemaleLevel_46": "",
        "CountMaleLevel_50": 2,
        "CountMaleLevel_46": 2
      },
      {
        "CNT": 9,
        "lk-url": "159solutions.com",
        "li-metrocity": "San Francisco",
        "lk-sic": 9999,
        "lk-employees": 7,
        "lk-salesmillion": 0.09,
        "lk-shortco": "159 Solutions",
        "CountMale": 7,
        "CountFemale": 2,
        "CountFemaleLevel_50": "",
        "CountFemaleLevel_46": "",
        "CountMaleLevel_50": 4,
        "CountMaleLevel_46": 4
      },
      {
        "CNT": 7,
        "lk-url": "15five.com",
        "li-metrocity": "New York",
        "lk-sic": 7372,
        "lk-employees": 11,
        "lk-salesmillion": 1.3,
        "lk-shortco": "15Five",
        "CountMale": 3,
        "CountFemale": 4,
        "CountFemaleLevel_50": 2,
        "CountFemaleLevel_46": 2,
        "CountMaleLevel_50": 2,
        "CountMaleLevel_46": 2
      },
      {
        "CNT": 5,
        "lk-url": "15love.org",
        "li-metrocity": "Albany",
        "lk-sic": 8641,
        "lk-employees": 7,
        "lk-salesmillion": 0.41,
        "lk-shortco": "15Love",
        "CountMale": 2,
        "CountFemale": 3,
        "CountFemaleLevel_50": 2,
        "CountFemaleLevel_46": 2,
        "CountMaleLevel_50": "",
        "CountMaleLevel_46": ""
      },
      {
        "CNT": 57,
        "lk-url": "1600avenue.com",
        "li-metrocity": "San Diego",
        "lk-sic": 7379,
        "lk-employees": 1,
        "lk-salesmillion": 0.05,
        "lk-shortco": "Department of Navy",
        "CountMale": 30,
        "CountFemale": 26,
        "CountFemaleLevel_50": 6,
        "CountFemaleLevel_46": 6,
        "CountMaleLevel_50": 7,
        "CountMaleLevel_46": 7
      },
      {
        "CNT": 7,
        "lk-url": "1607capital.com",
        "li-metrocity": "Richmond",
        "lk-sic": 6726,
        "lk-employees": 10,
        "lk-salesmillion": 2.4,
        "lk-shortco": "1607 Capital Partners",
        "CountMale": 4,
        "CountFemale": 3,
        "CountFemaleLevel_50": "",
        "CountFemaleLevel_46": "",
        "CountMaleLevel_50": 1,
        "CountMaleLevel_46": 1
      },
      {
        "CNT": 37,
        "lk-url": "160over90.com",
        "li-metrocity": "Atlanta",
        "lk-sic": 8742,
        "lk-employees": 45,
        "lk-salesmillion": 9.19,
        "lk-shortco": "160Over90",
        "CountMale": 24,
        "CountFemale": 13,
        "CountFemaleLevel_50": 11,
        "CountFemaleLevel_46": 11,
        "CountMaleLevel_50": 15,
        "CountMaleLevel_46": 14
      },
      {
        "CNT": 15,
        "lk-url": "160over90.com",
        "li-metrocity": "Chicago",
        "lk-sic": 8742,
        "lk-employees": 45,
        "lk-salesmillion": 9.19,
        "lk-shortco": "160Over90",
        "CountMale": 6,
        "CountFemale": 8,
        "CountFemaleLevel_50": 7,
        "CountFemaleLevel_46": 7,
        "CountMaleLevel_50": 6,
        "CountMaleLevel_46": 6
      },
      {
        "CNT": 75,
        "lk-url": "160over90.com",
        "li-metrocity": "Philadelphia",
        "lk-sic": 8742,
        "lk-employees": 45,
        "lk-salesmillion": 9.19,
        "lk-shortco": "160Over90",
        "CountMale": 35,
        "CountFemale": 40,
        "CountFemaleLevel_50": 16,
        "CountFemaleLevel_46": 16,
        "CountMaleLevel_50": 23,
        "CountMaleLevel_46": 23
      },
      {
        "CNT": 5,
        "lk-url": "161arw.ang.af.mil",
        "li-metrocity": "Phoenix",
        "lk-sic": 9224,
        "lk-employees": "",
        "lk-salesmillion": "",
        "lk-shortco": "161st Air Refueling Wing",
        "CountMale": 4,
        "CountFemale": 1,
        "CountFemaleLevel_50": "",
        "CountFemaleLevel_46": "",
        "CountMaleLevel_50": 2,
        "CountMaleLevel_46": 2
      },
      {
        "CNT": 6,
        "lk-url": "174powerglobal.com",
        "li-metrocity": "Phoenix",
        "lk-sic": 1711,
        "lk-employees": 1,
        "lk-salesmillion": 0.53,
        "lk-shortco": "174 Power Global",
        "CountMale": 6,
        "CountFemale": "",
        "CountFemaleLevel_50": "",
        "CountFemaleLevel_46": "",
        "CountMaleLevel_50": 5,
        "CountMaleLevel_46": 5
      },
      {
        "CNT": 18,
        "lk-url": "177milkstreet.com",
        "li-metrocity": "Boston",
        "lk-sic": 5143,
        "lk-employees": 2,
        "lk-salesmillion": 0.09,
        "lk-shortco": "Christopher Kimballs Milk Street",
        "CountMale": 6,
        "CountFemale": 12,
        "CountFemaleLevel_50": 5,
        "CountFemaleLevel_46": 5,
        "CountMaleLevel_50": 3,
        "CountMaleLevel_46": 3
      },
      {
        "CNT": 7,
        "lk-url": "18004injury.com",
        "li-metrocity": "San Francisco",
        "lk-sic": 8111,
        "lk-employees": 25,
        "lk-salesmillion": 3.51,
        "lk-shortco": "Kuvara Law Firm",
        "CountMale": 3,
        "CountFemale": 4,
        "CountFemaleLevel_50": 2,
        "CountFemaleLevel_46": 2,
        "CountMaleLevel_50": 1,
        "CountMaleLevel_46": 1
      },
      {
        "CNT": 46,
        "lk-url": "1800accountant.com",
        "li-metrocity": "New York",
        "lk-sic": 8721,
        "lk-employees": 30,
        "lk-salesmillion": 2.88,
        "lk-shortco": "1800Accountant",
        "CountMale": 34,
        "CountFemale": 11,
        "CountFemaleLevel_50": 2,
        "CountFemaleLevel_46": 2,
        "CountMaleLevel_50": 6,
        "CountMaleLevel_46": 6
      },
      {
        "CNT": 9,
        "lk-url": "1800asset.com",
        "li-metrocity": "Grand Rapids",
        "lk-sic": 7389,
        "lk-employees": "",
        "lk-salesmillion": "",
        "lk-shortco": "Miedema Asset Management",
        "CountMale": 6,
        "CountFemale": 3,
        "CountFemaleLevel_50": 1,
        "CountFemaleLevel_46": 1,
        "CountMaleLevel_50": 4,
        "CountMaleLevel_46": 4
      },
      {
        "CNT": 9,
        "lk-url": "1800flowersinc.com",
        "li-metrocity": "Orlando",
        "lk-sic": 4213,
        "lk-employees": 22,
        "lk-salesmillion": 5.1,
        "lk-shortco": "1800Flowerscom",
        "CountMale": 1,
        "CountFemale": 7,
        "CountFemaleLevel_50": 1,
        "CountFemaleLevel_46": 1,
        "CountMaleLevel_50": "",
        "CountMaleLevel_46": ""
      },
      {
        "CNT": 6,
        "lk-url": "1800gotjunk.com",
        "li-metrocity": "Detroit",
        "lk-sic": 6531,
        "lk-employees": 3,
        "lk-salesmillion": 0.34,
        "lk-shortco": "1800GotJunk",
        "CountMale": 6,
        "CountFemale": "",
        "CountFemaleLevel_50": "",
        "CountFemaleLevel_46": "",
        "CountMaleLevel_50": 2,
        "CountMaleLevel_46": 2
      },
      {
        "CNT": 6,
        "lk-url": "1800Remodel.com",
        "li-metrocity": "Los Angeles",
        "lk-sic": 1521,
        "lk-employees": 2,
        "lk-salesmillion": 0.27,
        "lk-shortco": "1800Remodelcom",
        "CountMale": 5,
        "CountFemale": 1,
        "CountFemaleLevel_50": "",
        "CountFemaleLevel_46": "",
        "CountMaleLevel_50": 3,
        "CountMaleLevel_46": 3
      },
      {
        "CNT": 7,
        "lk-url": "1800speakup.org",
        "li-metrocity": "Detroit",
        "lk-sic": 8641,
        "lk-employees": 3,
        "lk-salesmillion": 0.76,
        "lk-shortco": "Crime Stoppers of Michigan",
        "CountMale": 5,
        "CountFemale": 2,
        "CountFemaleLevel_50": 1,
        "CountFemaleLevel_46": 1,
        "CountMaleLevel_50": 1,
        "CountMaleLevel_46": 1
      },
      {
        "CNT": 5,
        "lk-url": "180business.com",
        "li-metrocity": "Oklahoma City",
        "lk-sic": 5812,
        "lk-employees": 832,
        "lk-salesmillion": 35,
        "lk-shortco": "O&M Restaurant",
        "CountMale": "",
        "CountFemale": 5,
        "CountFemaleLevel_50": 3,
        "CountFemaleLevel_46": 3,
        "CountMaleLevel_50": "",
        "CountMaleLevel_46": ""
      },
      {
        "CNT": 7,
        "lk-url": "183fw.ang.af.mil",
        "li-metrocity": "St Louis",
        "lk-sic": 9711,
        "lk-employees": "",
        "lk-salesmillion": "",
        "lk-shortco": "217th Engineering Installation Squadron",
        "CountMale": 7,
        "CountFemale": "",
        "CountFemaleLevel_50": "",
        "CountFemaleLevel_46": "",
        "CountMaleLevel_50": 2,
        "CountMaleLevel_46": 2
      },
      {
        "CNT": 41,
        "lk-url": "186arw.ang.af.mil",
        "li-metrocity": "Jackson",
        "lk-sic": 3721,
        "lk-employees": 2,
        "lk-salesmillion": 0.09,
        "lk-shortco": "Mississippi Air National Guard",
        "CountMale": 30,
        "CountFemale": 10,
        "CountFemaleLevel_50": 3,
        "CountFemaleLevel_46": 3,
        "CountMaleLevel_50": 5,
        "CountMaleLevel_46": 5
      },
      {
        "CNT": 30,
        "lk-url": "1871.com",
        "li-metrocity": "Chicago",
        "lk-sic": 8732,
        "lk-employees": 20,
        "lk-salesmillion": 6.42,
        "lk-shortco": "Opian Music",
        "CountMale": 15,
        "CountFemale": 14,
        "CountFemaleLevel_50": 12,
        "CountFemaleLevel_46": 12,
        "CountMaleLevel_50": 4,
        "CountMaleLevel_46": 4
      },
      {
        "CNT": 10,
        "lk-url": "1888baghouse.com",
        "li-metrocity": "Orange County",
        "lk-sic": 1761,
        "lk-employees": 130,
        "lk-salesmillion": 49.77,
        "lk-shortco": "Baghouse & Industrial Sheet Metal ServicesInc",
        "CountMale": 5,
        "CountFemale": 4,
        "CountFemaleLevel_50": "",
        "CountFemaleLevel_46": "",
        "CountMaleLevel_50": 1,
        "CountMaleLevel_46": 1
      },
      {
        "CNT": 6,
        "lk-url": "18birdies.com",
        "li-metrocity": "San Francisco",
        "lk-sic": 7992,
        "lk-employees": 4,
        "lk-salesmillion": 0.8,
        "lk-shortco": "18Birdies",
        "CountMale": 5,
        "CountFemale": 1,
        "CountFemaleLevel_50": "",
        "CountFemaleLevel_46": "",
        "CountMaleLevel_50": 3,
        "CountMaleLevel_46": 3
      },
      {
        "CNT": 12,
        "lk-url": "1910genetics.com",
        "li-metrocity": "Boston",
        "lk-sic": 8731,
        "lk-employees": 1,
        "lk-salesmillion": 0.04,
        "lk-shortco": "1910 Genetics",
        "CountMale": 11,
        "CountFemale": 1,
        "CountFemaleLevel_50": "",
        "CountFemaleLevel_46": "",
        "CountMaleLevel_50": 4,
        "CountMaleLevel_46": 4
      },
      {
        "CNT": 5,
        "lk-url": "1921consultants.com",
        "li-metrocity": "Austin",
        "lk-sic": "",
        "lk-employees": "",
        "lk-salesmillion": "",
        "lk-shortco": "",
        "CountMale": 4,
        "CountFemale": 1,
        "CountFemaleLevel_50": 1,
        "CountFemaleLevel_46": 1,
        "CountMaleLevel_50": 2,
        "CountMaleLevel_46": 2
      },
      {
        "CNT": 5,
        "lk-url": "1970sflashback.com",
        "li-metrocity": "Boston",
        "lk-sic": 8742,
        "lk-employees": 1,
        "lk-salesmillion": 0.03,
        "lk-shortco": 1970,
        "CountMale": 2,
        "CountFemale": 3,
        "CountFemaleLevel_50": 2,
        "CountFemaleLevel_46": 2,
        "CountMaleLevel_50": "",
        "CountMaleLevel_46": ""
      },
      {
        "CNT": 6,
        "lk-url": "19below.tv",
        "li-metrocity": "Kansas City",
        "lk-sic": 7812,
        "lk-employees": 12,
        "lk-salesmillion": 0.21,
        "lk-shortco": "19 Below",
        "CountMale": 5,
        "CountFemale": 1,
        "CountFemaleLevel_50": 1,
        "CountFemaleLevel_46": 1,
        "CountMaleLevel_50": 1,
        "CountMaleLevel_46": 1
      },
      {
        "CNT": 7,
        "lk-url": "19entertainment.com",
        "li-metrocity": "Los Angeles",
        "lk-sic": 7822,
        "lk-employees": "",
        "lk-salesmillion": "",
        "lk-shortco": "19 Entertainment",
        "CountMale": 3,
        "CountFemale": 4,
        "CountFemaleLevel_50": 1,
        "CountFemaleLevel_46": 1,
        "CountMaleLevel_50": 3,
        "CountMaleLevel_46": 3
      },
      {
        "CNT": 7,
        "lk-url": "19thnews.org",
        "li-metrocity": "Austin",
        "lk-sic": "",
        "lk-employees": "",
        "lk-salesmillion": "",
        "lk-shortco": "19th",
        "CountMale": "",
        "CountFemale": 7,
        "CountFemaleLevel_50": 6,
        "CountFemaleLevel_46": 6,
        "CountMaleLevel_50": "",
        "CountMaleLevel_46": ""
      },
      {
        "CNT": 11,
        "lk-url": "1beyond.com",
        "li-metrocity": "Boston",
        "lk-sic": 3861,
        "lk-employees": 15,
        "lk-salesmillion": 3.3,
        "lk-shortco": "Beyond",
        "CountMale": 11,
        "CountFemale": "",
        "CountFemaleLevel_50": "",
        "CountFemaleLevel_46": "",
        "CountMaleLevel_50": 4,
        "CountMaleLevel_46": 4
      },
      {
        "CNT": 13,
        "lk-url": "1bsa.org",
        "li-metrocity": "Birmingham",
        "lk-sic": 8641,
        "lk-employees": "",
        "lk-salesmillion": "",
        "lk-shortco": "Greater Alabama Boy Scout Council",
        "CountMale": 9,
        "CountFemale": 3,
        "CountFemaleLevel_50": 2,
        "CountFemaleLevel_46": 2,
        "CountMaleLevel_50": 9,
        "CountMaleLevel_46": 9
      },
      {
        "CNT": 5,
        "lk-url": "1choiceconstruction.com",
        "li-metrocity": "Charlotte",
        "lk-sic": 1542,
        "lk-employees": 13,
        "lk-salesmillion": 4,
        "lk-shortco": "1st Choice Construction Management",
        "CountMale": 4,
        "CountFemale": 1,
        "CountFemaleLevel_50": "",
        "CountFemaleLevel_46": "",
        "CountMaleLevel_50": 3,
        "CountMaleLevel_46": 3
      },
      {
        "CNT": 9,
        "lk-url": "1cor.com",
        "li-metrocity": "Philadelphia",
        "lk-sic": 6531,
        "lk-employees": 2,
        "lk-salesmillion": 0.33,
        "lk-shortco": "Enstar",
        "CountMale": 5,
        "CountFemale": 4,
        "CountFemaleLevel_50": 1,
        "CountFemaleLevel_46": 1,
        "CountMaleLevel_50": 4,
        "CountMaleLevel_46": 4
      },
      {
        "CNT": 11,
        "lk-url": "1cusa.com",
        "li-metrocity": "Atlanta",
        "lk-sic": 8741,
        "lk-employees": 600,
        "lk-salesmillion": 40.7,
        "lk-shortco": "CUSA",
        "CountMale": 5,
        "CountFemale": 5,
        "CountFemaleLevel_50": 4,
        "CountFemaleLevel_46": 4,
        "CountMaleLevel_50": 4,
        "CountMaleLevel_46": 4
      },
      {
        "CNT": 13,
        "lk-url": "1digitalagency.com",
        "li-metrocity": "Philadelphia",
        "lk-sic": 8641,
        "lk-employees": 5,
        "lk-salesmillion": 0.57,
        "lk-shortco": "1DigitalAgencycom",
        "CountMale": 8,
        "CountFemale": 4,
        "CountFemaleLevel_50": 1,
        "CountFemaleLevel_46": 1,
        "CountMaleLevel_50": 4,
        "CountMaleLevel_46": 4
      },
      {
        "CNT": 11,
        "lk-url": "1e.com",
        "li-metrocity": "New York",
        "lk-sic": 7371,
        "lk-employees": 30,
        "lk-salesmillion": 6.13,
        "lk-shortco": "",
        "CountMale": 8,
        "CountFemale": 3,
        "CountFemaleLevel_50": 2,
        "CountFemaleLevel_46": 2,
        "CountMaleLevel_50": 6,
        "CountMaleLevel_46": 6
      },
      {
        "CNT": 9,
        "lk-url": "1ffc.com",
        "li-metrocity": "Charlotte",
        "lk-sic": 6141,
        "lk-employees": "",
        "lk-salesmillion": "",
        "lk-shortco": "1st Franklin Financial",
        "CountMale": "",
        "CountFemale": 9,
        "CountFemaleLevel_50": 5,
        "CountFemaleLevel_46": 4,
        "CountMaleLevel_50": "",
        "CountMaleLevel_46": ""
      },
      {
        "CNT": 27,
        "lk-url": "1fsb.bank",
        "li-metrocity": "Omaha",
        "lk-sic": 6022,
        "lk-employees": 120,
        "lk-salesmillion": 40.94,
        "lk-shortco": "First State Bank Nebraska",
        "CountMale": 15,
        "CountFemale": 12,
        "CountFemaleLevel_50": 3,
        "CountFemaleLevel_46": 3,
        "CountMaleLevel_50": 7,
        "CountMaleLevel_46": 7
      },
      {
        "CNT": 6,
        "lk-url": "1micro.com",
        "li-metrocity": "Minneapolis",
        "lk-sic": 8742,
        "lk-employees": 25,
        "lk-salesmillion": 4.09,
        "lk-shortco": "1Micro",
        "CountMale": 5,
        "CountFemale": 1,
        "CountFemaleLevel_50": 1,
        "CountFemaleLevel_46": 1,
        "CountMaleLevel_50": 2,
        "CountMaleLevel_46": 2
      },
      {
        "CNT": 5,
        "lk-url": "1nb.com",
        "li-metrocity": "Dallas",
        "lk-sic": 6021,
        "lk-employees": 140,
        "lk-salesmillion": 22.73,
        "lk-shortco": "First National Bank & Trust of Ardmore Oklahoma",
        "CountMale": 4,
        "CountFemale": 1,
        "CountFemaleLevel_50": 1,
        "CountFemaleLevel_46": 1,
        "CountMaleLevel_50": 3,
        "CountMaleLevel_46": 3
      },
      {
        "CNT": 5,
        "lk-url": "1on1matchmaking.com",
        "li-metrocity": "Atlanta",
        "lk-sic": 7299,
        "lk-employees": 2,
        "lk-salesmillion": 0.07,
        "lk-shortco": "One on One Matchmaking",
        "CountMale": "",
        "CountFemale": 5,
        "CountFemaleLevel_50": 3,
        "CountFemaleLevel_46": 3,
        "CountMaleLevel_50": "",
        "CountMaleLevel_46": ""
      },
      {
        "CNT": 27,
        "lk-url": "1phx.com",
        "li-metrocity": "Phoenix",
        "lk-sic": "",
        "lk-employees": "",
        "lk-salesmillion": "",
        "lk-shortco": "None Of Your Business",
        "CountMale": 9,
        "CountFemale": 17,
        "CountFemaleLevel_50": 1,
        "CountFemaleLevel_46": 1,
        "CountMaleLevel_50": 1,
        "CountMaleLevel_46": 1
      },
      {
        "CNT": 5,
        "lk-url": "1phx.com",
        "li-metrocity": "Tucson",
        "lk-sic": "",
        "lk-employees": "",
        "lk-salesmillion": "",
        "lk-shortco": "None of your business",
        "CountMale": 4,
        "CountFemale": 1,
        "CountFemaleLevel_50": "",
        "CountFemaleLevel_46": "",
        "CountMaleLevel_50": 1,
        "CountMaleLevel_46": 1
      },
      {
        "CNT": 11,
        "lk-url": "1sale.com",
        "li-metrocity": "Miami",
        "lk-sic": 5651,
        "lk-employees": 145,
        "lk-salesmillion": 14.21,
        "lk-shortco": "1SaleADay",
        "CountMale": 7,
        "CountFemale": 3,
        "CountFemaleLevel_50": "",
        "CountFemaleLevel_46": "",
        "CountMaleLevel_50": 4,
        "CountMaleLevel_46": 4
      },
      {
        "CNT": 15,
        "lk-url": "1si.org",
        "li-metrocity": "Louisville",
        "lk-sic": 1731,
        "lk-employees": 40,
        "lk-salesmillion": 5.39,
        "lk-shortco": "One Southern Indiana",
        "CountMale": 4,
        "CountFemale": 10,
        "CountFemaleLevel_50": 7,
        "CountFemaleLevel_46": 7,
        "CountMaleLevel_50": 2,
        "CountMaleLevel_46": 2
      },
      {
        "CNT": 6,
        "lk-url": "1solar.com",
        "li-metrocity": "Salt Lake City",
        "lk-sic": 1711,
        "lk-employees": 25,
        "lk-salesmillion": 0.21,
        "lk-shortco": "1Solar",
        "CountMale": 4,
        "CountFemale": 2,
        "CountFemaleLevel_50": 1,
        "CountFemaleLevel_46": 1,
        "CountMaleLevel_50": 2,
        "CountMaleLevel_46": 2
      },
      {
        "CNT": 14,
        "lk-url": "1spirit.org",
        "li-metrocity": "New York",
        "lk-sic": 8611,
        "lk-employees": 15,
        "lk-salesmillion": 1.32,
        "lk-shortco": "One Spirit Learning Alliance",
        "CountMale": 4,
        "CountFemale": 9,
        "CountFemaleLevel_50": 3,
        "CountFemaleLevel_46": 3,
        "CountMaleLevel_50": 2,
        "CountMaleLevel_46": 2
      }
    
  ],
    "cities": [
      "Akron",
      "Albany",
      "Albuquerque",
      "Atlanta",
      "Augusta",
      "Austin",
      "Bakersfield",
      "Baltimore",
      "Baton Rouge",
      "Birmingham",
      "Boise",
      "Boston",
      "Buffalo",
      "Charleston",
      "Charlotte",
      "Chattanooga",
      "Chicago",
      "Cincinnati",
      "Cleveland",
      "Columbia",
      "Columbus",
      "Dallas",
      "Denver",
      "Des Moines",
      "Detroit",
      "El Paso",
      "Grand Rapids",
      "Greensboro",
      "Greenville",
      "Harrisburg",
      "Hartford",
      "Honolulu",
      "Houston",
      "Indianapolis",
      "Jackson",
      "Jacksonville",
      "Kansas City",
      "Knoxville",
      "Las Vegas",
      "Little Rock",
      "Los Angeles",
      "Louisville",
      "Madison",
      "Memphis",
      "Miami",
      "Milwaukee",
      "Minneapolis",
      "Nashville",
      "New Orleans",
      "New York",
      "Norfolk",
      "Oklahoma City",
      "Omaha",
      "Orange County",
      "Orlando",
      "Philadelphia",
      "Phoenix",
      "Pittsburgh",
      "Portland",
      "Providence",
      "Raleigh",
      "Richmond",
      "Rochester",
      "Sacramento",
      "Salt Lake City",
      "San Antonio",
      "San Diego",
      "San Francisco",
      "San Juan",
      "Seattle",
      "Silicon Valley",
      "Spokane",
      "Springfield",
      "St Louis",
      "Stockton",
      "Syracuse",
      "Tampa",
      "Tucson",
      "Tulsa",
      "Washington",
      "Wichita"
    ]
    
  }
